progkids/__init__.py
progkids/__progkids__.py
progkids/blocks.py
progkids/colors.py
progkids/creatures.py
progkids/directions.py
progkids/drones.py
progkids/entity.py
progkids/items.py
progkids/mc.py
progkids/particles.py
progkids/player.py
progkids/rails.py
progkids/util.py
progkids/weather.py
progkids/world.py
progkids-0.1.7.dist-info/LICENSE
progkids-0.1.7.dist-info/METADATA
progkids-0.1.7.dist-info/WHEEL
progkids-0.1.7.dist-info/top_level.txt
progkids-0.1.7.dist-info/RECORD
