Metadata-Version: 2.1
Name: progkids
Version: 0.1.7
Summary: Online coding school for kids - ProgKids
Home-page: UNKNOWN
Author: ProgKids Inc.
License: UNKNOWN
Platform: UNKNOWN
Classifier: Development Status :: 5 - Production/Stable
Classifier: Intended Audience :: Education
Classifier: Intended Audience :: Developers
Classifier: Topic :: Education
Classifier: Topic :: Games/Entertainment
Classifier: Programming Language :: Python :: 3
Classifier: License :: OSI Approved :: MIT License
Classifier: Operating System :: OS Independent
Requires-Python: >=3.6
Requires-Dist: python-socketio[client] (==4.6.1)
Requires-Dist: nanoid
